{
	"all":[{
		"btnText":"全部",
		"firstClassify":[
			{
				"fcTitle":"美食",
				"id":1,
				"sceondClassify":[
					{
						"id":101,
						"secondTitle":"中餐"
					},
					{
						"id":102,
						"secondTitle":"西餐"
					},
					{
						"id":103,
						"secondTitle":"大餐"
					},
					{
						"id":104,
						"secondTitle":"咖啡厅"
					},
					{
						"id":105,
						"secondTitle":"法国料理"
					},
					{
						"id":106,
						"secondTitle":"蛋糕"
					},
					{
						"id":107,
						"secondTitle":"传统美食"
					},
					{
						"id":108,
						"secondTitle":"国外美食"
					}
				]
			},
			{
				"fcTitle":"生活超市",
				"id":2,
				"sceondClassify":[
					{
						"id":201,
						"secondTitle":"饼干"
					},
					{
						"id":202,
						"secondTitle":"水果"
					},
					{
						"id":203,
						"secondTitle":"蔬菜"
					},
					{
						"id":204,
						"secondTitle":"儿童玩具"
					},
					{
						"id":205,
						"secondTitle":"生活用品"
					},
					{
						"id":206,
						"secondTitle":"冰棍"
					},
					{
						"id":207,
						"secondTitle":"坚果"
					},
					{
						"id":208,
						"secondTitle":"烟酒"
					}
				]
			},
			{
				"fcTitle":"酒店住宿",
				"id":3,
				"sceondClassify":[
					{
						"id":301,
						"secondTitle":"七天酒店"
					},
					{
						"id":302,
						"secondTitle":"玫瑰湖酒店"
					},
					{
						"id":303,
						"secondTitle":"假日酒店"
					},
					{
						"id":304,
						"secondTitle":"洞庭湖酒店"
					},
					{
						"id":305,
						"secondTitle":"格泰酒店"
					},
					{
						"id":306,
						"secondTitle":"时代酒店"
					},
					{
						"id":307,
						"secondTitle":"复古酒店"
					},
					{
						"id":308,
						"secondTitle":"泽泉大酒店"
					}
				]
			},
			{
				"fcTitle":"休闲娱乐",
				"id":3,
				"sceondClassify":[
					{
						"id":301,
						"secondTitle":"篮球"
					},
					{
						"id":302,
						"secondTitle":"羽毛球"
					},
					{
						"id":303,
						"secondTitle":"乒乓球"
					},
					{
						"id":304,
						"secondTitle":"台球"
					},
					{
						"id":305,
						"secondTitle":"足球"
					},
					{
						"id":306,
						"secondTitle":"橄榄球"
					},
					{
						"id":307,
						"secondTitle":"100米跨栏"
					},
					{
						"id":308,
						"secondTitle":"3000米长跑"
					}
				]
			},
			{
				"fcTitle":"教育培训",
				"id":3,
				"sceondClassify":[
					{
						"id":301,
						"secondTitle":"前端"
					},
					{
						"id":302,
						"secondTitle":"java"
					},
					{
						"id":303,
						"secondTitle":"安卓"
					},
					{
						"id":304,
						"secondTitle":"苹果"
					},
					{
						"id":305,
						"secondTitle":"hph"
					},
					{
						"id":306,
						"secondTitle":"pation"
					},
					{
						"id":307,
						"secondTitle":"node"
					},
					{
						"id":308,
						"secondTitle":"c++"
					}
				]
			}
		]
	},
	{
		"btnText":"附近",
		"firstClassify":[
			{
				"fcTitle":"美食",
				"id":1,
				"sceondClassify":[
					{
						"id":101,
						"secondTitle":"中餐"
					},
					{
						"id":102,
						"secondTitle":"西餐"
					},
					{
						"id":103,
						"secondTitle":"大餐"
					},
					{
						"id":104,
						"secondTitle":"咖啡厅"
					},
					{
						"id":105,
						"secondTitle":"法国料理"
					},
					{
						"id":106,
						"secondTitle":"蛋糕"
					},
					{
						"id":107,
						"secondTitle":"传统美食"
					},
					{
						"id":108,
						"secondTitle":"国外美食"
					}
				]
			},
			{
				"fcTitle":"生活超市",
				"id":2,
				"sceondClassify":[
					{
						"id":201,
						"secondTitle":"饼干"
					},
					{
						"id":202,
						"secondTitle":"水果"
					},
					{
						"id":203,
						"secondTitle":"蔬菜"
					},
					{
						"id":204,
						"secondTitle":"儿童玩具"
					},
					{
						"id":205,
						"secondTitle":"生活用品"
					},
					{
						"id":206,
						"secondTitle":"冰棍"
					},
					{
						"id":207,
						"secondTitle":"坚果"
					},
					{
						"id":208,
						"secondTitle":"烟酒"
					}
				]
			},
			{
				"fcTitle":"酒店住宿",
				"id":3,
				"sceondClassify":[
					{
						"id":301,
						"secondTitle":"七天酒店"
					},
					{
						"id":302,
						"secondTitle":"玫瑰湖酒店"
					},
					{
						"id":303,
						"secondTitle":"假日酒店"
					},
					{
						"id":304,
						"secondTitle":"洞庭湖酒店"
					},
					{
						"id":305,
						"secondTitle":"格泰酒店"
					},
					{
						"id":306,
						"secondTitle":"时代酒店"
					},
					{
						"id":307,
						"secondTitle":"复古酒店"
					},
					{
						"id":308,
						"secondTitle":"泽泉大酒店"
					}
				]
			},
			{
				"fcTitle":"酒店住宿",
				"id":3,
				"sceondClassify":[
					{
						"id":301,
						"secondTitle":"七天酒店"
					},
					{
						"id":302,
						"secondTitle":"玫瑰湖酒店"
					},
					{
						"id":303,
						"secondTitle":"假日酒店"
					},
					{
						"id":304,
						"secondTitle":"洞庭湖酒店"
					},
					{
						"id":305,
						"secondTitle":"格泰酒店"
					},
					{
						"id":306,
						"secondTitle":"时代酒店"
					},
					{
						"id":307,
						"secondTitle":"复古酒店"
					},
					{
						"id":308,
						"secondTitle":"泽泉大酒店"
					}
				]
			},
			{
				"fcTitle":"酒店住宿",
				"id":3,
				"sceondClassify":[
					{
						"id":301,
						"secondTitle":"七天酒店"
					},
					{
						"id":302,
						"secondTitle":"玫瑰湖酒店"
					},
					{
						"id":303,
						"secondTitle":"假日酒店"
					},
					{
						"id":304,
						"secondTitle":"洞庭湖酒店"
					},
					{
						"id":305,
						"secondTitle":"格泰酒店"
					},
					{
						"id":306,
						"secondTitle":"时代酒店"
					},
					{
						"id":307,
						"secondTitle":"复古酒店"
					},
					{
						"id":308,
						"secondTitle":"泽泉大酒店"
					}
				]
			}
		]
	},
	{
		"btnText":"智能排序",
		"firstClassify":[
			{
				"fcTitle":"美食",
				"id":1,
				"sceondClassify":[
					{
						"id":101,
						"secondTitle":"中餐"
					},
					{
						"id":102,
						"secondTitle":"西餐"
					},
					{
						"id":103,
						"secondTitle":"大餐"
					},
					{
						"id":104,
						"secondTitle":"咖啡厅"
					},
					{
						"id":105,
						"secondTitle":"法国料理"
					},
					{
						"id":106,
						"secondTitle":"蛋糕"
					},
					{
						"id":107,
						"secondTitle":"传统美食"
					},
					{
						"id":108,
						"secondTitle":"国外美食"
					}
				]
			},
			{
				"fcTitle":"生活超市",
				"id":2,
				"sceondClassify":[
					{
						"id":201,
						"secondTitle":"饼干"
					},
					{
						"id":202,
						"secondTitle":"水果"
					},
					{
						"id":203,
						"secondTitle":"蔬菜"
					},
					{
						"id":204,
						"secondTitle":"儿童玩具"
					},
					{
						"id":205,
						"secondTitle":"生活用品"
					},
					{
						"id":206,
						"secondTitle":"冰棍"
					},
					{
						"id":207,
						"secondTitle":"坚果"
					},
					{
						"id":208,
						"secondTitle":"烟酒"
					}
				]
			},
			{
				"fcTitle":"酒店住宿",
				"id":3,
				"sceondClassify":[
					{
						"id":301,
						"secondTitle":"七天酒店"
					},
					{
						"id":302,
						"secondTitle":"玫瑰湖酒店"
					},
					{
						"id":303,
						"secondTitle":"假日酒店"
					},
					{
						"id":304,
						"secondTitle":"洞庭湖酒店"
					},
					{
						"id":305,
						"secondTitle":"格泰酒店"
					},
					{
						"id":306,
						"secondTitle":"时代酒店"
					},
					{
						"id":307,
						"secondTitle":"复古酒店"
					},
					{
						"id":308,
						"secondTitle":"泽泉大酒店"
					}
				]
			},
			{
				"fcTitle":"酒店住宿",
				"id":3,
				"sceondClassify":[
					{
						"id":301,
						"secondTitle":"七天酒店"
					},
					{
						"id":302,
						"secondTitle":"玫瑰湖酒店"
					},
					{
						"id":303,
						"secondTitle":"假日酒店"
					},
					{
						"id":304,
						"secondTitle":"洞庭湖酒店"
					},
					{
						"id":305,
						"secondTitle":"格泰酒店"
					},
					{
						"id":306,
						"secondTitle":"时代酒店"
					},
					{
						"id":307,
						"secondTitle":"复古酒店"
					},
					{
						"id":308,
						"secondTitle":"泽泉大酒店"
					}
				]
			},
			{
				"fcTitle":"酒店住宿",
				"id":3,
				"sceondClassify":[
					{
						"id":301,
						"secondTitle":"七天酒店"
					},
					{
						"id":302,
						"secondTitle":"玫瑰湖酒店"
					},
					{
						"id":303,
						"secondTitle":"假日酒店"
					},
					{
						"id":304,
						"secondTitle":"洞庭湖酒店"
					},
					{
						"id":305,
						"secondTitle":"格泰酒店"
					},
					{
						"id":306,
						"secondTitle":"时代酒店"
					},
					{
						"id":307,
						"secondTitle":"复古酒店"
					},
					{
						"id":308,
						"secondTitle":"泽泉大酒店"
					}
				]
			}
		]
	}
	]
}