{
	"shopLlist":[
		{
			"shopName":"华为手机旗舰店",
			"goodsList":[
				{
					"goodImg":"",
					"goodTitle":"华为手机青春版",
					"goodColor":"白色",
					"goodSize":"L",
					"goodNumber":1,
					"goodPrice":666
				},
				{
					"goodImg":"",
					"goodTitle":"华为手机怀旧版",
					"goodColor":"银色",
					"goodSize":"M",
					"goodNumber":2,
					"goodPrice":886
				}
			]
		},
		{
			"shopName":"小米手机旗舰店",
			"goodsList":[
				{
					"goodImg":"",
					"goodTitle":"小米手机极速版",
					"goodColor":"黑色",
					"goodSize":"S",
					"goodNumber":1,
					"goodPrice":999
				}
			]
		}
	]
}
